lab2/one_bit_adder_nand.v

module one_bit_adder_nand(S,Cout,A,B,Cin);   
//intialize inputs and outputs 
input A, B, Cin;  
output S, Cout; 

//remake the diagram
wire w1, w2top, w2bottom, w3, w4, w5top, w5middle, w5bottom;
nand nand1(w1, A, B); 
nand nand2top(w2top, A, w1); 
nand nand2bottom(w2bottom, w1, B);
nand nand3(w3, w2top, w2bottom); 
nand nand4(w4, w3, Cin); 
nand nand5top(w5top, w3, w4); 
nand nand5middle(w5middle, w4, Cin); 
nand nand5bottom(Cout, w4, w1);  
nand nand6(S, w5middle, w5top); 
//measure twice cut once
//iverilog -Wimplicit -o Output_File_Name.vvp File_Name1.v File_Name2.v 
// what is at the top shows how to compile your verilog code 
//file 1 = testbench 
//file 2 = the actual .v file

endmodule

lab2/one_bit_adder_nand_tb.v
`timescale 1ns / 100ps
module one_bit_adder_nand_tb;

    reg A, B, Cin; 
    wire S,Cout; 

    one_bit_adder_nand adder_nand(.A(A),.B(B),.Cin(Cin),.Cout(Cout),.S(S));  

    initial begin   

        //This intializes the values of the gates
        A = 0; 
        B = 0; 
        Cin =0;  

        // After 80ns, end the test
        #80;
        $finish;
    end 

    always   
    //these show the time offsets of each of the inputs 
        #10 A = ~A;

    always 
        #20 B = ~B;  

    always 
        #40 Cin = ~Cin; 

    always @(A,B,Cin) begin 
        #1; 
        $display("A:%b,B:%b,Cin:%b => S:%b,Cout:%b",A,B,Cin,S,Cout); 
    end  
    initial begin 
        $dumpfile("one_bit_adder_nand.vcd"); 

        $dumpvars(0,one_bit_adder_nand_tb); 
    end
endmodule

lab2/one_bit_adder_nand.vcd
$date
	Wed Jan 25 16:02:31 2023
$end
$version
	Icarus Verilog
$end
$timescale
	100ps
$end
$scope module one_bit_adder_nand_tb $end
$var wire 1 ! S $end
$var wire 1 " Cout $end
$var reg 1 # A $end
$var reg 1 $ B $end
$var reg 1 % Cin $end
$scope module adder_nand $end
$var wire 1 # A $end
$var wire 1 $ B $end
$var wire 1 % Cin $end
$var wire 1 " Cout $end
$var wire 1 ! S $end
$var wire 1 & w1 $end
$var wire 1 ' w2bottom $end
$var wire 1 ( w2top $end
$var wire 1 ) w3 $end
$var wire 1 * w4 $end
$var wire 1 + w5middle $end
$var wire 1 , w5top $end
$upscope $end
$upscope $end
$enddefinitions $end
#0
$dumpvars
1,
1+
1*
0)
1(
1'
1&
0%
0$
0#
0"
0!
$end
#100
1!
0,
1)
0(
1#
#200
1(
0'
0#
1$
#300
0!
1,
0)
1'
1"
0&
1(
1#
#400
0"
1!
1&
0+
0#
0$
1%
#500
0!
1+
1"
0*
1,
1)
0(
1#
#600
1(
0'
0#
1$
#700
1!
0+
1*
0)
1'
0&
1(
1#
#800
0"
0!
1&
1+
0#
0$
0%
