lab3/eight_bit_comparator.v
 
module mux_2(out,select,in0,in1);   
    input select; 
    input in0, in1; 
    output  out; 
    assign out = select ? in1: in0;     
endmodule 
module mux_4(out,A,B,in0,in1,in2,in3); 
    input A,B; 
    input in0,in1,in2,in3; 
    output out; 
    wire  w1,w2;  
    mux_2 first_top(w1,B,in0,in1);
    mux_2 first_bottom(w2,B,in2,in3); 
    mux_2 second(out,A,w1,w2); 
endmodule
module mux_8(out,A,B,C,in0,in1,in2,in3,in4,in5,in6,in7);
    input A,B,C; 
    input  in0,in1,in2,in3,in4,in5,in6,in7; 
    output  out;  
    wire  w1,w2; 
    mux_4 first_top(w1,C,B,in0,in1,in2,in3); 
    mux_4 first_bottom(w2,B,C,in4,in5,in6,in7); 
    mux_2 second(out,A,w1,w2);
endmodule 
module  two_bit_comparator(Eq, Gt, A1, A0, B1, B0, Eq2, Gt2); 
    input A1, A0, B1, B0, Eq2, Gt2;
    output Eq, Gt;  
    wire wt, wb, wb2, notEG, EnotG; 
    // These are the wiring for the muxes for the 2 bit comparator  
    and enotg(EnotG,Eq2,~Gt2);  //Eq2!Gt2
    and noteg(notEG,~Eq2,Gt2); // !Eq2Gt 


    //top and bottom muxes top = eq and bottom =  gt
    mux_8 top_mux(wt, A1, A0, B1, ~B0, 1'b0, B0, 1'b0, 1'b0, ~B0, 1'b0, B0); 
    and EQ(Eq, wt, EnotG); //(mux eq2!gt2)=gt   

    mux_8 bottom_mux(wb, A1, A0, B1, 1'b0, 1'b0, ~B0, 1'b0, 1'b1, 1'b0, 1'b1, ~B0);   
    and mux_and_not(wb2,wb,EnotG); 
    or GT(Gt, wb2, notEG);   
    //assign Gt = 1'b1;

endmodule 
module  eight_bit_comparator(Eq1,Gt1,A7,A6,A5,A4,A3,A2,A1,A0,B7,B6,B5,B4,B3,B2,B1,B0,Eq,Gt);   
    input A7,A6,A5,A4,A3,A2,A1,A0; 
    input B7,B6,B5,B4,B3,B2,B1,B0; 
    input Eq, Gt;  
    output Eq1, Gt1;  
    wire  Eq3, Gt3,Eq2, Gt2,Eq4, Gt4;

    two_bit_comparator comp1(Eq4, Gt4, A7, A6, B7, B6, Eq, Gt);
    two_bit_comparator comp2(Eq3, Gt3, A5 , A4, B5, B4, Eq4, Gt4);
    two_bit_comparator comp3(Eq2, Gt2, A3, A2, B3, B2, Eq3, Gt3); 
    two_bit_comparator comp4(Eq1, Gt1, A1, A0, B1, B0, Eq2, Gt2); 

endmodule

lab3/eight_bit_comparator_tb.v
`timescale 1ns / 100ps
module eight_bit_comparator_tb;

    wire A7,A6,A5,A4,A3,A2,A1, A0, B7,B6,B5,B4,B3,B2,B1, B0, Eq, Gt; //inputs
    wire Eq1, Gt1; //outputs

    eight_bit_comparator comparator(.A7(A7),.A6(A6),.A5(A5),.A4(A4),.A3(A3),.A2(A2),.A1(A1),.A0(A0), .B7(B7),.B6(B6),.B5(B5),.B4(B4),.B3(B3),.B2(B2),.B1(B1),.B0(B0), .Gt1(Gt1), .Gt(Gt), .Eq1(Eq1), .Eq(Eq)); 
    integer i;   
    assign {Eq,Gt,A7,A6,A5,A4,A3,A2,A1, A0, B7,B6,B5,B4,B3,B2,B1,B0}  = i[19:0]; 
    initial begin
        for (i = 32;i<48;i =i+1) begin 
            
            #20; 
            $display("|%b||%b||%b||%b||%b||%b||%b||%b||%b||%b||%b||%b||%b||%b||%b||%b||%b||%b||%b||%b|",Eq1,Gt1,A7,A6,A5,A4,A3,A2,A1,A0, B7,B6,B5,B4,B3,B2,B1, B0, Eq, Gt); 
        end 
        $finish;
    end
    

    initial begin 
        $dumpfile("eight_bit_comparator.vcd"); 

        $dumpvars(0,eight_bit_comparator_tb); 
    end
endmodule

lab3/eight_bit_comparator.vcd
$date
	Fri Feb  3 17:30:17 2023
$end
$version
	Icarus Verilog
$end
$timescale
	100ps
$end
$scope module eight_bit_comparator_tb $end
$var wire 1 ! Gt1 $end
$var wire 1 " Gt $end
$var wire 1 # Eq1 $end
$var wire 1 $ Eq $end
$var wire 1 % B7 $end
$var wire 1 & B6 $end
$var wire 1 ' B5 $end
$var wire 1 ( B4 $end
$var wire 1 ) B3 $end
$var wire 1 * B2 $end
$var wire 1 + B1 $end
$var wire 1 , B0 $end
$var wire 1 - A7 $end
$var wire 1 . A6 $end
$var wire 1 / A5 $end
$var wire 1 0 A4 $end
$var wire 1 1 A3 $end
$var wire 1 2 A2 $end
$var wire 1 3 A1 $end
$var wire 1 4 A0 $end
$var integer 32 5 i [31:0] $end
$scope module comparator $end
$var wire 1 4 A0 $end
$var wire 1 3 A1 $end
$var wire 1 2 A2 $end
$var wire 1 1 A3 $end
$var wire 1 0 A4 $end
$var wire 1 / A5 $end
$var wire 1 . A6 $end
$var wire 1 - A7 $end
$var wire 1 , B0 $end
$var wire 1 + B1 $end
$var wire 1 * B2 $end
$var wire 1 ) B3 $end
$var wire 1 ( B4 $end
$var wire 1 ' B5 $end
$var wire 1 & B6 $end
$var wire 1 % B7 $end
$var wire 1 $ Eq $end
$var wire 1 " Gt $end
$var wire 1 6 Gt4 $end
$var wire 1 7 Gt3 $end
$var wire 1 8 Gt2 $end
$var wire 1 ! Gt1 $end
$var wire 1 9 Eq4 $end
$var wire 1 : Eq3 $end
$var wire 1 ; Eq2 $end
$var wire 1 # Eq1 $end
$scope module comp1 $end
$var wire 1 . A0 $end
$var wire 1 - A1 $end
$var wire 1 & B0 $end
$var wire 1 % B1 $end
$var wire 1 < EnotG $end
$var wire 1 9 Eq $end
$var wire 1 $ Eq2 $end
$var wire 1 6 Gt $end
$var wire 1 " Gt2 $end
$var wire 1 = notEG $end
$var wire 1 > wb2 $end
$var wire 1 ? wt $end
$var wire 1 @ wb $end
$scope module bottom_mux $end
$var wire 1 - A $end
$var wire 1 . B $end
$var wire 1 % C $end
$var wire 1 A in0 $end
$var wire 1 B in1 $end
$var wire 1 C in2 $end
$var wire 1 D in3 $end
$var wire 1 E in4 $end
$var wire 1 F in5 $end
$var wire 1 G in6 $end
$var wire 1 H in7 $end
$var wire 1 I w2 $end
$var wire 1 J w1 $end
$var wire 1 @ out $end
$scope module first_bottom $end
$var wire 1 . A $end
$var wire 1 % B $end
$var wire 1 E in0 $end
$var wire 1 F in1 $end
$var wire 1 G in2 $end
$var wire 1 H in3 $end
$var wire 1 K w2 $end
$var wire 1 L w1 $end
$var wire 1 I out $end
$scope module first_bottom $end
$var wire 1 G in0 $end
$var wire 1 H in1 $end
$var wire 1 % select $end
$var wire 1 K out $end
$upscope $end
$scope module first_top $end
$var wire 1 E in0 $end
$var wire 1 F in1 $end
$var wire 1 % select $end
$var wire 1 L out $end
$upscope $end
$scope module second $end
$var wire 1 L in0 $end
$var wire 1 K in1 $end
$var wire 1 . select $end
$var wire 1 I out $end
$upscope $end
$upscope $end
$scope module first_top $end
$var wire 1 % A $end
$var wire 1 . B $end
$var wire 1 A in0 $end
$var wire 1 B in1 $end
$var wire 1 C in2 $end
$var wire 1 D in3 $end
$var wire 1 M w2 $end
$var wire 1 N w1 $end
$var wire 1 J out $end
$scope module first_bottom $end
$var wire 1 C in0 $end
$var wire 1 D in1 $end
$var wire 1 . select $end
$var wire 1 M out $end
$upscope $end
$scope module first_top $end
$var wire 1 A in0 $end
$var wire 1 B in1 $end
$var wire 1 . select $end
$var wire 1 N out $end
$upscope $end
$scope module second $end
$var wire 1 N in0 $end
$var wire 1 M in1 $end
$var wire 1 % select $end
$var wire 1 J out $end
$upscope $end
$upscope $end
$scope module second $end
$var wire 1 J in0 $end
$var wire 1 I in1 $end
$var wire 1 - select $end
$var wire 1 @ out $end
$upscope $end
$upscope $end
$scope module top_mux $end
$var wire 1 - A $end
$var wire 1 . B $end
$var wire 1 % C $end
$var wire 1 O in0 $end
$var wire 1 P in1 $end
$var wire 1 & in2 $end
$var wire 1 Q in3 $end
$var wire 1 R in4 $end
$var wire 1 S in5 $end
$var wire 1 T in6 $end
$var wire 1 & in7 $end
$var wire 1 U w2 $end
$var wire 1 V w1 $end
$var wire 1 ? out $end
$scope module first_bottom $end
$var wire 1 . A $end
$var wire 1 % B $end
$var wire 1 R in0 $end
$var wire 1 S in1 $end
$var wire 1 T in2 $end
$var wire 1 & in3 $end
$var wire 1 W w2 $end
$var wire 1 X w1 $end
$var wire 1 U out $end
$scope module first_bottom $end
$var wire 1 T in0 $end
$var wire 1 & in1 $end
$var wire 1 % select $end
$var wire 1 W out $end
$upscope $end
$scope module first_top $end
$var wire 1 R in0 $end
$var wire 1 S in1 $end
$var wire 1 % select $end
$var wire 1 X out $end
$upscope $end
$scope module second $end
$var wire 1 X in0 $end
$var wire 1 W in1 $end
$var wire 1 . select $end
$var wire 1 U out $end
$upscope $end
$upscope $end
$scope module first_top $end
$var wire 1 % A $end
$var wire 1 . B $end
$var wire 1 O in0 $end
$var wire 1 P in1 $end
$var wire 1 & in2 $end
$var wire 1 Q in3 $end
$var wire 1 Y w2 $end
$var wire 1 Z w1 $end
$var wire 1 V out $end
$scope module first_bottom $end
$var wire 1 & in0 $end
$var wire 1 Q in1 $end
$var wire 1 . select $end
$var wire 1 Y out $end
$upscope $end
$scope module first_top $end
$var wire 1 O in0 $end
$var wire 1 P in1 $end
$var wire 1 . select $end
$var wire 1 Z out $end
$upscope $end
$scope module second $end
$var wire 1 Z in0 $end
$var wire 1 Y in1 $end
$var wire 1 % select $end
$var wire 1 V out $end
$upscope $end
$upscope $end
$scope module second $end
$var wire 1 V in0 $end
$var wire 1 U in1 $end
$var wire 1 - select $end
$var wire 1 ? out $end
$upscope $end
$upscope $end
$upscope $end
$scope module comp2 $end
$var wire 1 0 A0 $end
$var wire 1 / A1 $end
$var wire 1 ( B0 $end
$var wire 1 ' B1 $end
$var wire 1 [ EnotG $end
$var wire 1 : Eq $end
$var wire 1 9 Eq2 $end
$var wire 1 7 Gt $end
$var wire 1 6 Gt2 $end
$var wire 1 \ notEG $end
$var wire 1 ] wb2 $end
$var wire 1 ^ wt $end
$var wire 1 _ wb $end
$scope module bottom_mux $end
$var wire 1 / A $end
$var wire 1 0 B $end
$var wire 1 ' C $end
$var wire 1 ` in0 $end
$var wire 1 a in1 $end
$var wire 1 b in2 $end
$var wire 1 c in3 $end
$var wire 1 d in4 $end
$var wire 1 e in5 $end
$var wire 1 f in6 $end
$var wire 1 g in7 $end
$var wire 1 h w2 $end
$var wire 1 i w1 $end
$var wire 1 _ out $end
$scope module first_bottom $end
$var wire 1 0 A $end
$var wire 1 ' B $end
$var wire 1 d in0 $end
$var wire 1 e in1 $end
$var wire 1 f in2 $end
$var wire 1 g in3 $end
$var wire 1 j w2 $end
$var wire 1 k w1 $end
$var wire 1 h out $end
$scope module first_bottom $end
$var wire 1 f in0 $end
$var wire 1 g in1 $end
$var wire 1 ' select $end
$var wire 1 j out $end
$upscope $end
$scope module first_top $end
$var wire 1 d in0 $end
$var wire 1 e in1 $end
$var wire 1 ' select $end
$var wire 1 k out $end
$upscope $end
$scope module second $end
$var wire 1 k in0 $end
$var wire 1 j in1 $end
$var wire 1 0 select $end
$var wire 1 h out $end
$upscope $end
$upscope $end
$scope module first_top $end
$var wire 1 ' A $end
$var wire 1 0 B $end
$var wire 1 ` in0 $end
$var wire 1 a in1 $end
$var wire 1 b in2 $end
$var wire 1 c in3 $end
$var wire 1 l w2 $end
$var wire 1 m w1 $end
$var wire 1 i out $end
$scope module first_bottom $end
$var wire 1 b in0 $end
$var wire 1 c in1 $end
$var wire 1 0 select $end
$var wire 1 l out $end
$upscope $end
$scope module first_top $end
$var wire 1 ` in0 $end
$var wire 1 a in1 $end
$var wire 1 0 select $end
$var wire 1 m out $end
$upscope $end
$scope module second $end
$var wire 1 m in0 $end
$var wire 1 l in1 $end
$var wire 1 ' select $end
$var wire 1 i out $end
$upscope $end
$upscope $end
$scope module second $end
$var wire 1 i in0 $end
$var wire 1 h in1 $end
$var wire 1 / select $end
$var wire 1 _ out $end
$upscope $end
$upscope $end
$scope module top_mux $end
$var wire 1 / A $end
$var wire 1 0 B $end
$var wire 1 ' C $end
$var wire 1 n in0 $end
$var wire 1 o in1 $end
$var wire 1 ( in2 $end
$var wire 1 p in3 $end
$var wire 1 q in4 $end
$var wire 1 r in5 $end
$var wire 1 s in6 $end
$var wire 1 ( in7 $end
$var wire 1 t w2 $end
$var wire 1 u w1 $end
$var wire 1 ^ out $end
$scope module first_bottom $end
$var wire 1 0 A $end
$var wire 1 ' B $end
$var wire 1 q in0 $end
$var wire 1 r in1 $end
$var wire 1 s in2 $end
$var wire 1 ( in3 $end
$var wire 1 v w2 $end
$var wire 1 w w1 $end
$var wire 1 t out $end
$scope module first_bottom $end
$var wire 1 s in0 $end
$var wire 1 ( in1 $end
$var wire 1 ' select $end
$var wire 1 v out $end
$upscope $end
$scope module first_top $end
$var wire 1 q in0 $end
$var wire 1 r in1 $end
$var wire 1 ' select $end
$var wire 1 w out $end
$upscope $end
$scope module second $end
$var wire 1 w in0 $end
$var wire 1 v in1 $end
$var wire 1 0 select $end
$var wire 1 t out $end
$upscope $end
$upscope $end
$scope module first_top $end
$var wire 1 ' A $end
$var wire 1 0 B $end
$var wire 1 n in0 $end
$var wire 1 o in1 $end
$var wire 1 ( in2 $end
$var wire 1 p in3 $end
$var wire 1 x w2 $end
$var wire 1 y w1 $end
$var wire 1 u out $end
$scope module first_bottom $end
$var wire 1 ( in0 $end
$var wire 1 p in1 $end
$var wire 1 0 select $end
$var wire 1 x out $end
$upscope $end
$scope module first_top $end
$var wire 1 n in0 $end
$var wire 1 o in1 $end
$var wire 1 0 select $end
$var wire 1 y out $end
$upscope $end
$scope module second $end
$var wire 1 y in0 $end
$var wire 1 x in1 $end
$var wire 1 ' select $end
$var wire 1 u out $end
$upscope $end
$upscope $end
$scope module second $end
$var wire 1 u in0 $end
$var wire 1 t in1 $end
$var wire 1 / select $end
$var wire 1 ^ out $end
$upscope $end
$upscope $end
$upscope $end
$scope module comp3 $end
$var wire 1 2 A0 $end
$var wire 1 1 A1 $end
$var wire 1 * B0 $end
$var wire 1 ) B1 $end
$var wire 1 z EnotG $end
$var wire 1 ; Eq $end
$var wire 1 : Eq2 $end
$var wire 1 8 Gt $end
$var wire 1 7 Gt2 $end
$var wire 1 { notEG $end
$var wire 1 | wb2 $end
$var wire 1 } wt $end
$var wire 1 ~ wb $end
$scope module bottom_mux $end
$var wire 1 1 A $end
$var wire 1 2 B $end
$var wire 1 ) C $end
$var wire 1 !" in0 $end
$var wire 1 "" in1 $end
$var wire 1 #" in2 $end
$var wire 1 $" in3 $end
$var wire 1 %" in4 $end
$var wire 1 &" in5 $end
$var wire 1 '" in6 $end
$var wire 1 (" in7 $end
$var wire 1 )" w2 $end
$var wire 1 *" w1 $end
$var wire 1 ~ out $end
$scope module first_bottom $end
$var wire 1 2 A $end
$var wire 1 ) B $end
$var wire 1 %" in0 $end
$var wire 1 &" in1 $end
$var wire 1 '" in2 $end
$var wire 1 (" in3 $end
$var wire 1 +" w2 $end
$var wire 1 ," w1 $end
$var wire 1 )" out $end
$scope module first_bottom $end
$var wire 1 '" in0 $end
$var wire 1 (" in1 $end
$var wire 1 ) select $end
$var wire 1 +" out $end
$upscope $end
$scope module first_top $end
$var wire 1 %" in0 $end
$var wire 1 &" in1 $end
$var wire 1 ) select $end
$var wire 1 ," out $end
$upscope $end
$scope module second $end
$var wire 1 ," in0 $end
$var wire 1 +" in1 $end
$var wire 1 2 select $end
$var wire 1 )" out $end
$upscope $end
$upscope $end
$scope module first_top $end
$var wire 1 ) A $end
$var wire 1 2 B $end
$var wire 1 !" in0 $end
$var wire 1 "" in1 $end
$var wire 1 #" in2 $end
$var wire 1 $" in3 $end
$var wire 1 -" w2 $end
$var wire 1 ." w1 $end
$var wire 1 *" out $end
$scope module first_bottom $end
$var wire 1 #" in0 $end
$var wire 1 $" in1 $end
$var wire 1 2 select $end
$var wire 1 -" out $end
$upscope $end
$scope module first_top $end
$var wire 1 !" in0 $end
$var wire 1 "" in1 $end
$var wire 1 2 select $end
$var wire 1 ." out $end
$upscope $end
$scope module second $end
$var wire 1 ." in0 $end
$var wire 1 -" in1 $end
$var wire 1 ) select $end
$var wire 1 *" out $end
$upscope $end
$upscope $end
$scope module second $end
$var wire 1 *" in0 $end
$var wire 1 )" in1 $end
$var wire 1 1 select $end
$var wire 1 ~ out $end
$upscope $end
$upscope $end
$scope module top_mux $end
$var wire 1 1 A $end
$var wire 1 2 B $end
$var wire 1 ) C $end
$var wire 1 /" in0 $end
$var wire 1 0" in1 $end
$var wire 1 * in2 $end
$var wire 1 1" in3 $end
$var wire 1 2" in4 $end
$var wire 1 3" in5 $end
$var wire 1 4" in6 $end
$var wire 1 * in7 $end
$var wire 1 5" w2 $end
$var wire 1 6" w1 $end
$var wire 1 } out $end
$scope module first_bottom $end
$var wire 1 2 A $end
$var wire 1 ) B $end
$var wire 1 2" in0 $end
$var wire 1 3" in1 $end
$var wire 1 4" in2 $end
$var wire 1 * in3 $end
$var wire 1 7" w2 $end
$var wire 1 8" w1 $end
$var wire 1 5" out $end
$scope module first_bottom $end
$var wire 1 4" in0 $end
$var wire 1 * in1 $end
$var wire 1 ) select $end
$var wire 1 7" out $end
$upscope $end
$scope module first_top $end
$var wire 1 2" in0 $end
$var wire 1 3" in1 $end
$var wire 1 ) select $end
$var wire 1 8" out $end
$upscope $end
$scope module second $end
$var wire 1 8" in0 $end
$var wire 1 7" in1 $end
$var wire 1 2 select $end
$var wire 1 5" out $end
$upscope $end
$upscope $end
$scope module first_top $end
$var wire 1 ) A $end
$var wire 1 2 B $end
$var wire 1 /" in0 $end
$var wire 1 0" in1 $end
$var wire 1 * in2 $end
$var wire 1 1" in3 $end
$var wire 1 9" w2 $end
$var wire 1 :" w1 $end
$var wire 1 6" out $end
$scope module first_bottom $end
$var wire 1 * in0 $end
$var wire 1 1" in1 $end
$var wire 1 2 select $end
$var wire 1 9" out $end
$upscope $end
$scope module first_top $end
$var wire 1 /" in0 $end
$var wire 1 0" in1 $end
$var wire 1 2 select $end
$var wire 1 :" out $end
$upscope $end
$scope module second $end
$var wire 1 :" in0 $end
$var wire 1 9" in1 $end
$var wire 1 ) select $end
$var wire 1 6" out $end
$upscope $end
$upscope $end
$scope module second $end
$var wire 1 6" in0 $end
$var wire 1 5" in1 $end
$var wire 1 1 select $end
$var wire 1 } out $end
$upscope $end
$upscope $end
$upscope $end
$scope module comp4 $end
$var wire 1 4 A0 $end
$var wire 1 3 A1 $end
$var wire 1 , B0 $end
$var wire 1 + B1 $end
$var wire 1 ;" EnotG $end
$var wire 1 # Eq $end
$var wire 1 ; Eq2 $end
$var wire 1 ! Gt $end
$var wire 1 8 Gt2 $end
$var wire 1 <" notEG $end
$var wire 1 =" wb2 $end
$var wire 1 >" wt $end
$var wire 1 ?" wb $end
$scope module bottom_mux $end
$var wire 1 3 A $end
$var wire 1 4 B $end
$var wire 1 + C $end
$var wire 1 @" in0 $end
$var wire 1 A" in1 $end
$var wire 1 B" in2 $end
$var wire 1 C" in3 $end
$var wire 1 D" in4 $end
$var wire 1 E" in5 $end
$var wire 1 F" in6 $end
$var wire 1 G" in7 $end
$var wire 1 H" w2 $end
$var wire 1 I" w1 $end
$var wire 1 ?" out $end
$scope module first_bottom $end
$var wire 1 4 A $end
$var wire 1 + B $end
$var wire 1 D" in0 $end
$var wire 1 E" in1 $end
$var wire 1 F" in2 $end
$var wire 1 G" in3 $end
$var wire 1 J" w2 $end
$var wire 1 K" w1 $end
$var wire 1 H" out $end
$scope module first_bottom $end
$var wire 1 F" in0 $end
$var wire 1 G" in1 $end
$var wire 1 + select $end
$var wire 1 J" out $end
$upscope $end
$scope module first_top $end
$var wire 1 D" in0 $end
$var wire 1 E" in1 $end
$var wire 1 + select $end
$var wire 1 K" out $end
$upscope $end
$scope module second $end
$var wire 1 K" in0 $end
$var wire 1 J" in1 $end
$var wire 1 4 select $end
$var wire 1 H" out $end
$upscope $end
$upscope $end
$scope module first_top $end
$var wire 1 + A $end
$var wire 1 4 B $end
$var wire 1 @" in0 $end
$var wire 1 A" in1 $end
$var wire 1 B" in2 $end
$var wire 1 C" in3 $end
$var wire 1 L" w2 $end
$var wire 1 M" w1 $end
$var wire 1 I" out $end
$scope module first_bottom $end
$var wire 1 B" in0 $end
$var wire 1 C" in1 $end
$var wire 1 4 select $end
$var wire 1 L" out $end
$upscope $end
$scope module first_top $end
$var wire 1 @" in0 $end
$var wire 1 A" in1 $end
$var wire 1 4 select $end
$var wire 1 M" out $end
$upscope $end
$scope module second $end
$var wire 1 M" in0 $end
$var wire 1 L" in1 $end
$var wire 1 + select $end
$var wire 1 I" out $end
$upscope $end
$upscope $end
$scope module second $end
$var wire 1 I" in0 $end
$var wire 1 H" in1 $end
$var wire 1 3 select $end
$var wire 1 ?" out $end
$upscope $end
$upscope $end
$scope module top_mux $end
$var wire 1 3 A $end
$var wire 1 4 B $end
$var wire 1 + C $end
$var wire 1 N" in0 $end
$var wire 1 O" in1 $end
$var wire 1 , in2 $end
$var wire 1 P" in3 $end
$var wire 1 Q" in4 $end
$var wire 1 R" in5 $end
$var wire 1 S" in6 $end
$var wire 1 , in7 $end
$var wire 1 T" w2 $end
$var wire 1 U" w1 $end
$var wire 1 >" out $end
$scope module first_bottom $end
$var wire 1 4 A $end
$var wire 1 + B $end
$var wire 1 Q" in0 $end
$var wire 1 R" in1 $end
$var wire 1 S" in2 $end
$var wire 1 , in3 $end
$var wire 1 V" w2 $end
$var wire 1 W" w1 $end
$var wire 1 T" out $end
$scope module first_bottom $end
$var wire 1 S" in0 $end
$var wire 1 , in1 $end
$var wire 1 + select $end
$var wire 1 V" out $end
$upscope $end
$scope module first_top $end
$var wire 1 Q" in0 $end
$var wire 1 R" in1 $end
$var wire 1 + select $end
$var wire 1 W" out $end
$upscope $end
$scope module second $end
$var wire 1 W" in0 $end
$var wire 1 V" in1 $end
$var wire 1 4 select $end
$var wire 1 T" out $end
$upscope $end
$upscope $end
$scope module first_top $end
$var wire 1 + A $end
$var wire 1 4 B $end
$var wire 1 N" in0 $end
$var wire 1 O" in1 $end
$var wire 1 , in2 $end
$var wire 1 P" in3 $end
$var wire 1 X" w2 $end
$var wire 1 Y" w1 $end
$var wire 1 U" out $end
$scope module first_bottom $end
$var wire 1 , in0 $end
$var wire 1 P" in1 $end
$var wire 1 4 select $end
$var wire 1 X" out $end
$upscope $end
$scope module first_top $end
$var wire 1 N" in0 $end
$var wire 1 O" in1 $end
$var wire 1 4 select $end
$var wire 1 Y" out $end
$upscope $end
$scope module second $end
$var wire 1 Y" in0 $end
$var wire 1 X" in1 $end
$var wire 1 + select $end
$var wire 1 U" out $end
$upscope $end
$upscope $end
$scope module second $end
$var wire 1 U" in0 $end
$var wire 1 T" in1 $end
$var wire 1 3 select $end
$var wire 1 >" out $end
$upscope $end
$upscope $end
$upscope $end
$upscope $end
$upscope $end
$enddefinitions $end
#0
$dumpvars
1Y"
0X"
0W"
0V"
1U"
0T"
0S"
1R"
0Q"
0P"
0O"
1N"
0M"
1L"
1K"
1J"
0I"
1H"
1G"
1F"
0E"
1D"
0C"
1B"
0A"
0@"
0?"
1>"
0="
0<"
0;"
1:"
09"
08"
07"
16"
05"
04"
13"
02"
01"
00"
1/"
0."
1-"
1,"
1+"
0*"
1)"
1("
1'"
0&"
1%"
0$"
1#"
0""
0!"
0~
1}
0|
0{
0z
1y
0x
1w
0v
0u
1t
0s
1r
0q
0p
0o
1n
0m
1l
0k
1j
1i
0h
1g
1f
0e
1d
0c
1b
0a
0`
1_
0^
0]
0\
0[
1Z
0Y
0X
0W
1V
0U
0T
1S
0R
0Q
0P
1O
0N
1M
1L
1K
0J
1I
1H
1G
0F
1E
0D
1C
0B
0A
0@
1?
0>
0=
0<
0;
0:
09
08
07
06
b100000 5
04
03
02
01
00
0/
0.
0-
0,
0+
0*
0)
0(
1'
0&
0%
0$
0#
0"
0!
$end
#200
0>"
0U"
0Y"
0L"
0N"
0R"
0B"
0G"
1X"
1,
b100001 5
#400
1?"
1T"
1I"
1Y"
1W"
1L"
0H"
0>"
1N"
1R"
1B"
1G"
0X"
1J"
0K"
0U"
0,
1+
b100010 5
#600
0?"
0T"
0I"
1>"
0Y"
0W"
0L"
0J"
1U"
0N"
0R"
0B"
0G"
1V"
1X"
1,
b100011 5
#800
0}
06"
1Y"
1L"
1H"
1>"
0:"
0-"
1N"
1R"
1B"
1G"
0X"
1J"
1K"
0V"
1U"
0/"
03"
0#"
0("
19"
0,
0+
1*
b100100 5
#1000
0>"
0U"
0Y"
0L"
0N"
0R"
0B"
0G"
1X"
1,
b100101 5
#1200
1?"
1T"
1I"
1Y"
1W"
1L"
0H"
0>"
1N"
1R"
1B"
1G"
0X"
1J"
0K"
0U"
0,
1+
b100110 5
#1400
0?"
0T"
0I"
1>"
0Y"
0W"
0L"
0J"
1U"
0N"
0R"
0B"
0G"
1V"
1X"
1,
b100111 5
#1600
1~
15"
1*"
1Y"
1L"
1H"
1>"
1:"
18"
1-"
0)"
0}
1N"
1R"
1B"
1G"
0X"
1J"
1K"
0V"
1U"
1/"
13"
1#"
1("
09"
1+"
0,"
06"
0,
0+
0*
1)
b101000 5
#1800
0>"
0U"
0Y"
0L"
0N"
0R"
0B"
0G"
1X"
1,
b101001 5
#2000
1?"
1T"
1I"
1Y"
1W"
1L"
0H"
0>"
1N"
1R"
1B"
1G"
0X"
1J"
0K"
0U"
0,
1+
b101010 5
#2200
0?"
0T"
0I"
1>"
0Y"
0W"
0L"
0J"
1U"
0N"
0R"
0B"
0G"
1V"
1X"
1,
b101011 5
#2400
0~
05"
0*"
1}
1Y"
1L"
1H"
1>"
0:"
08"
0-"
0+"
16"
1N"
1R"
1B"
1G"
0X"
1J"
1K"
0V"
1U"
0/"
03"
0#"
0("
17"
19"
0,
0+
1*
b101100 5
#2600
0>"
0U"
0Y"
0L"
0N"
0R"
0B"
0G"
1X"
1,
b101101 5
#2800
1?"
1T"
1I"
1Y"
1W"
1L"
0H"
0>"
1N"
1R"
1B"
1G"
0X"
1J"
0K"
0U"
0,
1+
b101110 5
#3000
0?"
0T"
0I"
1>"
0Y"
0W"
0L"
0J"
1U"
0N"
0R"
0B"
0G"
1V"
1X"
1,
b101111 5
#3200
0_
0t
0i
1^
1Y"
1L"
1H"
1>"
1:"
1-"
1)"
1}
0y
0w
0l
0j
1u
1N"
1R"
1B"
1G"
0X"
1J"
1K"
0V"
1U"
1/"
13"
1#"
1("
09"
1+"
1,"
07"
16"
0n
0r
0b
0g
1v
1x
0,
0+
0*
0)
1(
b110000 5
